pmyning/__init__.py
pmyning/io/__init__.py
pmyning/io/xes.py
pmyning-0.1.1.dist-info/METADATA
pmyning-0.1.1.dist-info/WHEEL
pmyning-0.1.1.dist-info/RECORD
